tox_py.py
tox_py-1.3.1.dist-info/LICENSE
tox_py-1.3.1.dist-info/METADATA
tox_py-1.3.1.dist-info/WHEEL
tox_py-1.3.1.dist-info/entry_points.txt
tox_py-1.3.1.dist-info/top_level.txt
tox_py-1.3.1.dist-info/RECORD
