Metadata-Version: 2.1
Name: tox-py
Version: 1.3.1
Summary: Adds the --py flag to tox to run environments matching a given Python interpreter.
Home-page: https://github.com/adamchainz/tox-py
Author: Adam Johnson
Author-email: me@adamj.eu
License: MIT License
Project-URL: Changelog, https://github.com/adamchainz/tox-py/blob/main/HISTORY.rst
Project-URL: Twitter, https://twitter.com/adamchainz
Keywords: tox
Classifier: Development Status :: 7 - Inactive
Classifier: Framework :: tox
Classifier: Intended Audience :: Developers
Classifier: License :: OSI Approved :: MIT License
Classifier: Natural Language :: English
Classifier: Operating System :: OS Independent
Classifier: Programming Language :: Python :: 3 :: Only
Classifier: Programming Language :: Python :: 3
Classifier: Programming Language :: Python :: 3.7
Classifier: Programming Language :: Python :: 3.8
Classifier: Programming Language :: Python :: 3.9
Classifier: Programming Language :: Python :: 3.10
Classifier: Programming Language :: Python :: 3.11
Classifier: Typing :: Typed
Requires-Python: >=3.7
License-File: LICENSE
Requires-Dist: tox (<4,>=3)
